[
  {
    "heading_pic": "products/bathtubs/bathtube_header.jpg",
    "prod_name": "BathTubs",
    "more_products": null,
    "products": [
      {
        "pic": "products/bathtubs/Hindware_Marina_Bathtub.jpg",
        "name": "Hindware Strauss Bathtub",
        "price": "27,390",
        "link": "https://hindware.com/product/straussn-bathtub/"
      },
      {
        "pic": "products/bathtubs/Trendy_Bathtub.jpg",
        "name": "Hindware Trendy Bathtub",
        "price": "15,590",
        "link": "https://hindware.com/product/trendy-bathtub/"
      },
      {
        "pic": "products/bathtubs/Vantage_Bathtub.jpg",
        "name": "Hindware Vantage Bathtub",
        "price": "39,950",
        "link": "https://hindware.com/product/vantage-n-bathtub/"
      },
      {
        "pic": "products/bathtubs/Marina_Plus_Bathtub.jpg",
        "name": "Marina Plus Bathtub",
        "price": "14,960",
        "link": "https://hindware.com/product/marina-plus-bathtub/"
      },
      {
        "pic": "products/bathtubs/Hindware_Marina_Bathtub.jpg",
        "name": "Hindware Marina Bathtub",
        "price": "14,460",
        "link": "https://hindware.com/product/marina-bathtub/"
      },
      {
        "pic": "products/bathtubs/Trendy_Plus_Bathtub.jpg",
        "name": "Trendy Plus Bathtub",
        "price": "16,210",
        "link": "https://hindware.com/product/trendy-plus-2-bathtub/"
      }
    ]
  }
]
